Workbook
Name BS_Check: Assumptions!$E$132
Name BS_Check: Scenarios!$E$126
Name BS_Check: Summary!$E$112
Name BS_Check: Model!$E$141
Name Currency: Assumptions!$F$21
Name L_Scenarios: Scenarios!$D$8:$D$10
Name Million: Assumptions!$F$11
Name S_Scenarios: Scenarios!$E$7
Name Scenario_Used: Scenarios!$D$7

Sheet Exam Info
A8: Financial Modeling Institute – AFM Level 1 Exam
A9: Exam Information
A12: Candidate ID: | D12: FMI0178605
A14: Candidate Name: | D14: Ovoke Ohwoganohwo

Sheet Cover Page
B3: =Model!B2 -> Farley-Jamieson Inc.
B5: ="Financial Statement from: "&$D$11+1&" to "&$D$11+5 -> Financial Statement from: 2024 to 2028
B7: Modeler | D7: Ovoke Ohwoganohwo
B9: Version | D9: Ver 1.01
B11: Base Year | D11: 2023
B13: Circularity in Model (OFF) | D13: Net Interest Expense in Income Statement

Sheet Summary
B2: Farley-Jamieson Inc. | I2: ="Financial Model: "&L5&" to "&P5 -> Financial Model: 2024 to 2028
B3: Summary | I3: =IF(BS_Check=0,"BS Check: OK","BS Check: Error") -> BS Check: OK | K3: =Scenario_Used -> Scenario: Base Case
I4: Actual | J4: Actual | K4: Actual | L4: Forecast | M4: Forecast | N4: Forecast | O4: Forecast | P4: Forecast
E5: Unit | F5: Trend | I5: 2021 | J5: =I5+1 -> 2022 | K5: =J5+1 -> 2023 | L5: =K5+1 -> 2024 | M5: =L5+1 -> 2025 | N5: =M5+1 -> 2026 | O5: =N5+1 -> 2027 | P5: =O5+1 -> 2028
B9: Analysis Based On: Base Case
C11: Net Revenue
D12: Net Revenue | E12: $'m | I12: 5118.4 | J12: 5392.4 | K12: 5277.2 | L12: 5839.4112 | M12: 6070.9021 | N12: 6310.318 | O12: 6557.9103 | P12: 6734
D13: Net Revenue Growth Rate | E13: % | J13: 0.053532354 | K13: -0.0213634 | L13: 0.10653589 | M13: 0.039642857 | N13: 0.03943662 | O13: 0.039236111 | P13: 0.026851492
C15: EBITDA
D16: EBITDA | E16: $'m | I16: 817.3 | J16: 909.4 | K16: 779.3 | L16: 1166.1126 | M16: 1203.2135 | N16: 1239.3864 | O16: 1274.4489 | P16: 1258.9381
D17: EBITDA Margin | E17: % | I17: 0.15967881 | J17: 0.16864476 | K17: 0.14767301 | L17: 0.19969696 | M17: 0.19819352 | N17: 0.19640633 | O17: 0.19433765 | P17: 0.1869525
D18: EBITDA Growth Rate | E18: % | J18: 0.11268812 | K18: -0.14306136 | L18: 0.4963591 | M18: 0.031815821 | N18: 0.030063564 | O18: 0.028290201 | P18: -0.012170551
C20: Net Income
D21: Net Income | E21: $'m | I21: 345.7 | J21: 349.5 | K21: 267.2 | L21: 604.21444 | M21: 628.67605 | N21: 654.33978 | O21: 679.87219 | P21: 673.21634
D22: Net Profit Margin | E22: % | I22: 0.067540638 | J22: 0.064813441 | K22: 0.050632911 | L22: 0.10347181 | M22: 0.10355562 | N22: 0.10369363 | O22: 0.10367208 | P22: 0.099972726
D23: Net Income Growth Rate | E23: % | J23: 0.01099219 | K23: -0.23547926 | L23: 1.2612816 | M23: 0.04048498 | N23: 0.040821857 | O23: 0.039020113 | P23: -0.0097898607
C25: Dupont Analysis
D26: ROE | E26: % | I26: 0.19213027 | J26: 0.20526223 | K26: 0.16599366 | L26: 0.31759984 | M26: 0.27720406 | N26: 0.24226001 | O26: 0.21636983 | P26: 0.18805032
D27: Net Profit Margin | E27: % | I27: 0.067540638 | J27: 0.064813441 | K27: 0.050632911 | L27: 0.10347181 | M27: 0.10355562 | N27: 0.10369363 | O27: 0.10367208 | P27: 0.099972726
D28: Assets Turnover | E28: times | I28: 0.92240043 | J28: 0.94719831 | K28: 0.9787092 | L28: 1.0561663 | M28: 1.0623035 | N28: 1.057748 | O28: 1.0519121 | P28: 1.0368487
D29: Financial Leverage | E29: times | I29: 3.0839771 | J29: 3.3435132 | K29: 3.3496925 | L29: 2.9062029 | M29: 2.5291682 | N29: 2.2244776 | O29: 1.9976526 | P29: 1.8267161
B34: Analysis Based On: Best Case
C36: Net Revenue
D37: Net Revenue | E37: $'m | I37: 5118.4 | J37: 5392.4 | K37: 5277.2 | L37: 6486.0192 | M37: 6808.9303 | N37: 7146.4998 | O37: 7307.3 | P37: 7407.4
D38: Net Revenue Growth Rate | E38: % | J38: 0.053532354 | K38: -0.0213634 | L38: 0.2290645 | M38: 0.049785714 | N38: 0.049577465 | O38: 0.02250056 | P38: 0.01369863
C40: EBITDA
D41: EBITDA | E41: $'m | I41: 817.3 | J41: 909.4 | K41: 779.3 | L41: 1826.1095 | M41: 1980.6949 | N41: 2142.3876 | O41: 2182.7863 | P41: 2180.396
D42: EBITDA Margin | E42: % | I42: 0.15967881 | J42: 0.16864476 | K42: 0.14767301 | L42: 0.2815455 | M42: 0.29089664 | N42: 0.29978139 | O42: 0.29871311 | P42: 0.29435376
D43: EBITDA Growth Rate | E43: % | J43: 0.11268812 | K43: -0.14306136 | L43: 1.3432689 | M43: 0.084652876 | N43: 0.081634334 | O43: 0.018856858 | P43: -0.0010950562
C45: Net Income
D46: Net Income | E46: $'m | I46: 345.7 | J46: 349.5 | K46: 267.2 | L46: 1037.3271 | M46: 1145.5276 | N46: 1261.4735 | O46: 1300.3688 | P46: 1312.3573
D47: Net Profit Margin | E47: % | I47: 0.067540638 | J47: 0.064813441 | K47: 0.050632911 | L47: 0.15993278 | M47: 0.168239 | N47: 0.17651627 | O47: 0.17795476 | P47: 0.17716841
D48: Net Income Growth Rate | E48: % | J48: 0.01099219 | K48: -0.23547926 | L48: 2.8822122 | M48: 0.10430706 | N48: 0.10121609 | O48: 0.030833286 | P48: 0.0092192551
C50: Dupont Analysis
D51: ROE | E51: % | I51: 0.19213027 | J51: 0.20526223 | K51: 0.16599366 | L51: 0.47497475 | M51: 0.39735638 | N51: 0.34024015 | O51: 0.28564286 | P51: 0.24279025
D52: Net Profit Margin | E52: % | I52: 0.067540638 | J52: 0.064813441 | K52: 0.050632911 | L52: 0.15993278 | M52: 0.168239 | N52: 0.17651627 | O52: 0.17795476 | P52: 0.17716841
D53: Assets Turnover | E53: times | I53: 0.92240043 | J53: 0.94719831 | K53: 0.9787092 | L53: 1.1165658 | M53: 1.0757889 | N53: 1.024855 | O53: 0.95693855 | P53: 0.89207242
D54: Financial Leverage | E54: times | I54: 3.0839771 | J54: 3.3435132 | K54: 3.3496925 | L54: 2.6597982 | M54: 2.1999055 | N54: 1.8877028 | O54: 1.6833604 | P54: 1.5416227
B59: Analysis Based On: Worst Case
C61: Net Revenue
D62: Net Revenue | E62: $'m | I62: 5118.4 | J62: 5392.4 | K62: 5277.2 | L62: 5493.3193 | M62: 5655.3722 | N62: 5821.0507 | O62: 5990.4271 | P62: 6163.575
D63: Net Revenue Growth Rate | E63: % | J63: 0.053532354 | K63: -0.0213634 | L63: 0.040953394 | M63: 0.0295 | N63: 0.029295775 | O63: 0.029097222 | P63: 0.02890411
C65: EBITDA
D66: EBITDA | E66: $'m | I66: 817.3 | J66: 909.4 | K66: 779.3 | L66: 807.03052 | M66: 748.80619 | N66: 683.57124 | O66: 610.87107 | P66: 530.22568
D67: EBITDA Margin | E67: % | I67: 0.15967881 | J67: 0.16864476 | K67: 0.14767301 | L67: 0.14691127 | M67: 0.13240617 | N67: 0.1174309 | O67: 0.10197454 | P67: 0.086025672
D68: EBITDA Growth Rate | E68: % | J68: 0.11268812 | K68: -0.14306136 | L68: 0.035583889 | M68: -0.072146388 | N68: -0.087118599 | O68: -0.10635347 | P68: -0.13201703
C70: Net Income
D71: Net Income | E71: $'m | I71: 345.7 | J71: 349.5 | K71: 267.2 | L71: 368.52189 | M71: 322.1823 | N71: 269.50037 | O71: 210.57945 | P71: 145.15365
D72: Net Profit Margin | E72: % | I72: 0.067540638 | J72: 0.064813441 | K72: 0.050632911 | L72: 0.067085467 | M72: 0.056969247 | N72: 0.046297548 | O72: 0.035152661 | P72: 0.023550237
D73: Net Income Growth Rate | E73: % | J73: 0.01099219 | K73: -0.23547926 | L73: 0.37919868 | M73: -0.12574448 | N73: -0.16351589 | O73: -0.2186302 | P73: -0.31069413
C75: Dupont Analysis
D76: ROE | E76: % | I76: 0.19213027 | J76: 0.20526223 | K76: 0.16599366 | L76: 0.21067552 | M76: 0.16772096 | N76: 0.12738535 | O76: 0.093057569 | P76: 0.060979109
D77: Net Profit Margin | E77: % | I77: 0.067540638 | J77: 0.064813441 | K77: 0.050632911 | L77: 0.067085467 | M77: 0.056969247 | N77: 0.046297548 | O77: 0.035152661 | P77: 0.023550237
D78: Assets Turnover | E78: times | I78: 0.92240043 | J78: 0.94719831 | K78: 0.9787092 | L78: 1.0216084 | M78: 1.0211403 | N78: 1.0023408 | O78: 0.98724953 | P78: 0.97634784
D79: Financial Leverage | E79: times | I79: 3.0839771 | J79: 3.3435132 | K79: 3.3496925 | L79: 3.073981 | M79: 2.903955 | N79: 2.7929546 | O79: 2.741646 | P79: 2.7393298
A86: SUMMARY GENERATOR
B87: {="Analysis Based On: "&INDEX(L_Scenarios,S_Scenarios)} -> Analysis Based On: Base Case
C89: Net Revenue
D90: =Model!D21 -> Net Revenue | E90: =Model!E21 -> $'m | I90: =Model!I21 -> 5118.4 | J90: =Model!J21 -> 5392.4 | K90: =Model!K21 -> 5277.2 | L90: =Model!L21 -> 5839.4112 | M90: =Model!M21 -> 6070.9021 | N90: =Model!N21 -> 6310.318 | O90: =Model!O21 -> 6557.9103 | P90: =Model!P21 -> 6734
D91: Net Revenue Growth Rate | E91: % | J91: =J90/I90-1 -> 0.053532354 | K91: =K90/J90-1 -> -0.0213634 | L91: =L90/K90-1 -> 0.10653589 | M91: =M90/L90-1 -> 0.039642857 | N91: =N90/M90-1 -> 0.03943662 | O91: =O90/N90-1 -> 0.039236111 | P91: =P90/O90-1 -> 0.026851492
C93: EBITDA
D94: =Model!D28 -> EBITDA | E94: =Model!E28 -> $'m | I94: =Model!I28 -> 817.3 | J94: =Model!J28 -> 909.4 | K94: =Model!K28 -> 779.3 | L94: =Model!L28 -> 1166.1126 | M94: =Model!M28 -> 1203.2135 | N94: =Model!N28 -> 1239.3864 | O94: =Model!O28 -> 1274.4489 | P94: =Model!P28 -> 1258.9381
D95: =Model!D47 -> EBITDA Margin | E95: =Model!E47 -> % | I95: =Model!I47 -> 0.15967881 | J95: =Model!J47 -> 0.16864476 | K95: =Model!K47 -> 0.14767301 | L95: =Model!L47 -> 0.19969696 | M95: =Model!M47 -> 0.19819352 | N95: =Model!N47 -> 0.19640633 | O95: =Model!O47 -> 0.19433765 | P95: =Model!P47 -> 0.1869525
D96: EBITDA Growth Rate | E96: % | J96: =J94/I94-1 -> 0.11268812 | K96: =K94/J94-1 -> -0.14306136 | L96: =L94/K94-1 -> 0.4963591 | M96: =M94/L94-1 -> 0.031815821 | N96: =N94/M94-1 -> 0.030063564 | O96: =O94/N94-1 -> 0.028290201 | P96: =P94/O94-1 -> -0.012170551
C98: Net Income
D99: =Model!D41 -> Net Income | E99: =Model!E41 -> $'m | I99: =Model!I41 -> 345.7 | J99: =Model!J41 -> 349.5 | K99: =Model!K41 -> 267.2 | L99: =Model!L41 -> 604.21444 | M99: =Model!M41 -> 628.67605 | N99: =Model!N41 -> 654.33978 | O99: =Model!O41 -> 679.87219 | P99: =Model!P41 -> 673.21634
D100: =Model!D50 -> Net Profit Margin | E100: =Model!E50 -> % | I100: =Model!I50 -> 0.067540638 | J100: =Model!J50 -> 0.064813441 | K100: =Model!K50 -> 0.050632911 | L100: =Model!L50 -> 0.10347181 | M100: =Model!M50 -> 0.10355562 | N100: =Model!N50 -> 0.10369363 | O100: =Model!O50 -> 0.10367208 | P100: =Model!P50 -> 0.099972726
D101: Net Income Growth Rate | E101: % | J101: =J99/I99-1 -> 0.01099219 | K101: =K99/J99-1 -> -0.23547926 | L101: =L99/K99-1 -> 1.2612816 | M101: =M99/L99-1 -> 0.04048498 | N101: =N99/M99-1 -> 0.040821857 | O101: =O99/N99-1 -> 0.039020113 | P101: =P99/O99-1 -> -0.0097898607
C103: =Model!C48 -> Dupont Analysis
D104: =Model!D49 -> ROE | E104: =Model!E49 -> % | I104: =Model!I49 -> 0.19213027 | J104: =Model!J49 -> 0.20526223 | K104: =Model!K49 -> 0.16599366 | L104: =Model!L49 -> 0.31759984 | M104: =Model!M49 -> 0.27720406 | N104: =Model!N49 -> 0.24226001 | O104: =Model!O49 -> 0.21636983 | P104: =Model!P49 -> 0.18805032
D105: =Model!D50 -> Net Profit Margin | E105: =Model!E50 -> % | I105: =Model!I50 -> 0.067540638 | J105: =Model!J50 -> 0.064813441 | K105: =Model!K50 -> 0.050632911 | L105: =Model!L50 -> 0.10347181 | M105: =Model!M50 -> 0.10355562 | N105: =Model!N50 -> 0.10369363 | O105: =Model!O50 -> 0.10367208 | P105: =Model!P50 -> 0.099972726
D106: =Model!D51 -> Assets Turnover | E106: =Model!E51 -> times | I106: =Model!I51 -> 0.92240043 | J106: =Model!J51 -> 0.94719831 | K106: =Model!K51 -> 0.9787092 | L106: =Model!L51 -> 1.0561663 | M106: =Model!M51 -> 1.0623035 | N106: =Model!N51 -> 1.057748 | O106: =Model!O51 -> 1.0519121 | P106: =Model!P51 -> 1.0368487
D107: =Model!D52 -> Financial Leverage | E107: =Model!E52 -> times | I107: =Model!I52 -> 3.0839771 | J107: =Model!J52 -> 3.3435132 | K107: =Model!K52 -> 3.3496925 | L107: =Model!L52 -> 2.9062029 | M107: =Model!M52 -> 2.5291682 | N107: =Model!N52 -> 2.2244776 | O107: =Model!O52 -> 1.9976526 | P107: =Model!P52 -> 1.8267161

Sheet Assumptions
B2: Farley-Jamieson Inc. | I2: ="Financial Model: "&L5&" to "&P5 -> Financial Model: 2024 to 2028
B3: Assumptions | I3: =IF(BS_Check=0,"BS Check: OK","BS Check: Error") -> BS Check: OK | K3: =Scenario_Used -> Scenario: Base Case
I4: Actual | J4: Actual | K4: Actual | L4: Forecast | M4: Forecast | N4: Forecast | O4: Forecast | P4: Forecast
E5: Unit | F5: Input | I5: 2021 | J5: =I5+1 -> 2022 | K5: =J5+1 -> 2023 | L5: =K5+1 -> 2024 | M5: =L5+1 -> 2025 | N5: =M5+1 -> 2026 | O5: =N5+1 -> 2027 | P5: =O5+1 -> 2028
A8: GENERAL ASSUMPTION
D10: Days in the Year | E10: Days | I10: =DATE(I5,12,31)-DATE(I5,1,1)+1 -> 365 | J10: =DATE(J5,12,31)-DATE(J5,1,1)+1 -> 365 | K10: =DATE(K5,12,31)-DATE(K5,1,1)+1 -> 365 | L10: =DATE(L5,12,31)-DATE(L5,1,1)+1 -> 366 | M10: =DATE(M5,12,31)-DATE(M5,1,1)+1 -> 365 | N10: =DATE(N5,12,31)-DATE(N5,1,1)+1 -> 365 | O10: =DATE(O5,12,31)-DATE(O5,1,1)+1 -> 365 | P10: =DATE(P5,12,31)-DATE(P5,1,1)+1 -> 366
D11: Million | E11: Constant | F11: 1000000
B14: Style Guide
D16: Number | E16: Number | F16: 1234.5
D17: Input | E17: Number
D18: Percentage | E18: Number | F18: 0.123
D19: Multiple | E19: Number | F19: 12.3
D20: Linked | E20: Number
D21: Currency | E21: Number | F21: $'m
D22: Units | E22: Text | F22: Text
D23: Heading 1 | E23: Text | F23: Text
B26: Revenue Assumption
D28: Net Revenue | E28: $/unit | K28: 32421
D29: Gross Revenue | E29: $/unit | K29: 34463
D30: Freight & Warehouse costs | E30: $/unit | K30: 2042
D32: =Scenarios!B33 -> Sales Prices Scenarios | E32: $/unit | L32: =Scenarios!L35 -> 35000 | M32: =Scenarios!M35 -> 35500 | N32: =Scenarios!N35 -> 36000 | O32: =Scenarios!O35 -> 36500 | P32: =Scenarios!P35 -> 37000
D33: =Scenarios!B16 -> Sales Volume Scenarios | E33: % | L33: =Scenarios!L18 -> 0.025 | M33: =Scenarios!M18 -> 0.025 | N33: =Scenarios!N18 -> 0.025 | O33: =Scenarios!O18 -> 0.025 | P33: =Scenarios!P18 -> 0.025
D35: Freight & Warehousing costs | E35: % | L35: =Scenarios!L27 -> 0.03 | M35: =Scenarios!M27 -> 0.03 | N35: =Scenarios!N27 -> 0.03 | O35: =Scenarios!O27 -> 0.03 | P35: =Scenarios!P27 -> 0.03
D37: Manufacturing Capacity | E37: units | F37: 182000
B40: Operating Cost Assumption
C42: Cost of Sales
D43: Variable Cost | E43: % | F43: 0.6
D44: Fixed Cost | E44: % | F44: 0.4
D45: Total Cost | E45: % | F45: =SUM(F43:F44) -> 1
D47: =Scenarios!B25 -> Cost Inflation Scenarios | E47: % | L47: =Scenarios!L27 -> 0.03 | M47: =Scenarios!M27 -> 0.03 | N47: =Scenarios!N27 -> 0.03 | O47: =Scenarios!O27 -> 0.03 | P47: =Scenarios!P27 -> 0.03
D49: Selling General & Administration (“SG&A”) expense | E49: =Currency -> $'m | L49: 1200
B54: Capex and Depreciation Assumption
D56: Capex Additions | E56: =Currency -> $'m | L56: 225 | M56: 225 | N56: 225 | O56: 225 | P56: 225
D58: Depreciation Method | E58: Straight-Line method
C60: Useful Life
D61: Existing assets | E61: Years | F61: 12
D62: New Assets | E62: Years | F62: 18
B65: Income Tax Assumptions
D67: Company’s tax rate | E67: % | F67: 0.35
D69: Reduction due to Timing Differences | E69: =Currency -> $'m | L69: 100 | M69: 100 | N69: 100 | O69: 100 | P69: 100
B72: Working Capital Assumption
D74: =D10 -> Days in the Year | E74: =E10 -> Days | I74: =I10 -> 365 | J74: =J10 -> 365 | K74: =K10 -> 365 | L74: =L10 -> 366 | M74: =M10 -> 365 | N74: =N10 -> 365 | O74: =O10 -> 365 | P74: =P10 -> 366
C76: Extract
D77: =Model!D21 -> Net Revenue | E77: =Model!E21 -> $'m | I77: =Model!I21 -> 5118.4 | J77: =Model!J21 -> 5392.4 | K77: =Model!K21 -> 5277.2
D78: =Model!D23 -> Cost of Sales | E78: =Model!E23 -> $'m | I78: =Model!I23 -> 3243.3 | J78: =Model!J23 -> 3403.7 | K78: =Model!K23 -> 3322.3
C80: Balances
D81: =Model!D103 -> Accounts Receivable | E81: =Currency -> $'m | I81: =Model!I103 -> 787.2 | J81: =Model!J103 -> 882.6 | K81: =Model!K103 -> 869.2
D82: =Model!D104 -> Inventory | E82: =Currency -> $'m | I82: =Model!I104 -> 915.9 | J82: =Model!J104 -> 951 | K82: =Model!K104 -> 929.9
D83: =Model!D105 -> Other | E83: =Currency -> $'m | I83: =Model!I105 -> 185.8 | J83: =Model!J105 -> 181.3 | K83: =Model!K105 -> 183.7
D84: Current Assets | E84: =Currency -> $'m | I84: =SUM(I81:I83) -> 1888.9 | J84: =SUM(J81:J83) -> 2014.9 | K84: =SUM(K81:K83) -> 1982.8
D86: =Model!D119 -> Accounts Payable | E86: =Currency -> $'m | I86: =Model!I119 -> 375 | J86: =Model!J119 -> 378 | K86: =Model!K119 -> 349.2
D87: =Model!D120 -> Other | E87: =Currency -> $'m | I87: =Model!I120 -> 4.9 | J87: =Model!J120 -> 5.8 | K87: =Model!K120 -> 5.3
D88: Current Liabilities | E88: =Currency -> $'m | I88: =SUM(I86:I87) -> 379.9 | J88: =SUM(J86:J87) -> 383.8 | K88: =SUM(K86:K87) -> 354.5
C90: Days
D91: =D81 -> Accounts Receivable | E91: Days | I91: =I81/I77*I74 -> 56.136293 | J91: =J81/J77*J74 -> 59.741303 | K91: =K81/K77*K74 -> 60.118624 | L91: 58.665406 | M91: 58.665406 | N91: 58.665406 | O91: 58.665406 | P91: 58.665406
D92: =D82 -> Inventory | E92: Days | I92: =I82/I$78*I$74 -> 103.07511 | J92: =J82/J$78*J$74 -> 101.98167 | K92: =K82/K$78*K$74 -> 102.16221 | L92: 102.40633 | M92: 102.40633 | N92: 102.40633 | O92: 102.40633 | P92: 102.40633
D93: =D83 -> Other | E93: Days | I93: =I83/I$78*I$74 -> 20.909876 | J93: =J83/J$78*J$74 -> 19.441931 | K93: =K83/K$78*K$74 -> 20.181952 | L93: 20.17792 | M93: 20.17792 | N93: 20.17792 | O93: 20.17792 | P93: 20.17792
D96: =D86 -> Accounts Payable | E96: Days | I96: =I86/I$78*I$74 -> 42.202386 | J96: =J86/J$78*J$74 -> 40.5353 | K96: =K86/K$78*K$74 -> 38.364386 | L96: 40.367357 | M96: 40.367357 | N96: 40.367357 | O96: 40.367357 | P96: 40.367357
D97: =D87 -> Other | E97: Days | I97: =I87/I$78*I$74 -> 0.55144452 | J97: =J87/J$78*J$74 -> 0.62197021 | K97: =K87/K$78*K$74 -> 0.58227734 | L97: 0.58523069 | M97: 0.58523069 | N97: 0.58523069 | O97: 0.58523069 | P97: 0.58523069
B100: Equity Assumption
C102: Preferred Shares
D103: Issuance of Preferred Shares | E103: =Currency -> $'m | L103: 0 | M103: 50 | N103: 0 | O103: 0 | P103: 0
D104: Dividend Payout | E104: % | F104: 0.0925
C106: Common Share
D107: Common Share repurchases | E107: =Currency -> $'m | L107: 100 | M107: 100 | N107: 0 | O107: 0 | P107: 0
D108: =D104 -> Dividend Payout | E108: =E104 -> % | F108: 0.35
B111: Debt Assumption
C113: Fixed Rate Debt
D114: Fixed Rate Term Debt | E114: % | F114: 0.071
D116: Revolver | E116: % | F116: 0.075
C118: Variable Rate Debt
D119: Variable Rate Term Debt | E119: %
D120: SOFR | E120: % | F120: 0.053
D123: Total Debt/EBITDA | E123: Spread to SOFR
D124: 0 | E124: 0.01
D125: 1 | E125: 0.015
D126: 2 | E126: 0.02
D127: 3 | E127: 0.025
D128: 4 | E128: 0.0275
D129: 4.5 | E129: 0.03
D131: Excess cash | E131: % | F131: 0.035
D133: Amortization on the fixed rate term debt | E133: =Currency -> $'m | L133: 150 | M133: 150 | N133: 150 | O133: 150 | P133: 150
D134: Amortization on the variable rate term debt | E134: =Currency -> $'m | L134: 75 | M134: 75 | N134: 75 | O134: 75 | P134: 75
B137: Other Assumptions
D139: Cost Adjustments - Gain / (Loss) - Operation | E139: =Currency -> $'m | L139: 0 | M139: 0 | N139: 0 | O139: 0 | P139: 0
D140: Cost Adjustments - Gain / (Loss) - Financing | E140: =Currency -> $'m | L140: 0 | M140: 0 | N140: 0 | O140: 0 | P140: 0
D141: Other - Operating Activities | E141: =Currency -> $'m | L141: 0 | M141: 0 | N141: 0 | O141: 0 | P141: 0
D142: Other - Investing Activities | E142: =Currency -> $'m | L142: 0 | M142: 0 | N142: 0 | O142: 0 | P142: 0
D143: Other - Financing Activities | E143: =Currency -> $'m | L143: 0 | M143: 0 | N143: 0 | O143: 0 | P143: 0
D144: =Model!D74 -> Asset Dispositions | E144: =Currency -> $'m | L144: 0 | M144: 0 | N144: 0 | O144: 0 | P144: 0
D145: =Model!D110 -> Intangibles | E145: =Currency -> $'m | L145: 0 | M145: 0 | N145: 0 | O145: 0 | P145: 0
D146: Other Long-Term Assets | E146: =Currency -> $'m | L146: 0 | M146: 0 | N146: 0 | O146: 0 | P146: 0
D147: Other Long-Term Liabilities | E147: =Currency -> $'m | L147: 0 | M147: 0 | N147: 0 | O147: 0 | P147: 0
D148: Other Shareholders’ Equity | E148: =Currency -> $'m | L148: 0 | M148: 0 | N148: 0 | O148: 0 | P148: 0
D149: Goodwill | E149: =Currency -> $'m | L149: 0 | M149: 0 | N149: 0 | O149: 0 | P149: 0

Sheet Scenarios
B2: Farley-Jamieson Inc. | I2: ="Financial Model: "&L5&" to "&P5 -> Financial Model: 2024 to 2028
B3: Scenarios | I3: =IF(BS_Check=0,"BS Check: OK","BS Check: Error") -> BS Check: OK | K3: =Scenario_Used -> Scenario: Base Case
I4: Actual | J4: Actual | K4: Actual | L4: Forecast | M4: Forecast | N4: Forecast | O4: Forecast | P4: Forecast
E5: Unit | F5: Input | I5: 2021 | J5: =I5+1 -> 2022 | K5: =J5+1 -> 2023 | L5: =K5+1 -> 2024 | M5: =L5+1 -> 2025 | N5: =M5+1 -> 2026 | O5: =N5+1 -> 2027 | P5: =O5+1 -> 2028
D7: {="Scenario: "&INDEX(L_Scenarios,S_Scenarios)} -> Scenario: Base Case | E7: 1
D8: Base Case
D9: Best Case
D10: Worst Case
B16: Sales Volume Scenarios
D18: Used in the Model | E18: % | L18: {=INDEX(L19:L21,S_Scenarios)} -> 0.025 | M18: {=INDEX(M19:M21,S_Scenarios)} -> 0.025 | N18: {=INDEX(N19:N21,S_Scenarios)} -> 0.025 | O18: {=INDEX(O19:O21,S_Scenarios)} -> 0.025 | P18: {=INDEX(P19:P21,S_Scenarios)} -> 0.025
D19: {=L_Scenarios} -> Base Case | E19: % | L19: 0.025 | M19: 0.025 | N19: 0.025 | O19: 0.025 | P19: 0.025
D20: Best Case | E20: % | L20: 0.035 | M20: 0.035 | N20: 0.035 | O20: 0.035 | P20: 0.035
D21: Worst Case | E21: % | L21: 0.015 | M21: 0.015 | N21: 0.015 | O21: 0.015 | P21: 0.015
B25: Cost Inflation Scenarios
D27: Used in the Model | E27: % | L27: {=INDEX(L28:L30,S_Scenarios)} -> 0.03 | M27: {=INDEX(M28:M30,S_Scenarios)} -> 0.03 | N27: {=INDEX(N28:N30,S_Scenarios)} -> 0.03 | O27: {=INDEX(O28:O30,S_Scenarios)} -> 0.03 | P27: {=INDEX(P28:P30,S_Scenarios)} -> 0.03
D28: {=L_Scenarios} -> Base Case | E28: % | L28: 0.03 | M28: 0.03 | N28: 0.03 | O28: 0.03 | P28: 0.03
D29: Best Case | E29: % | L29: 0.02 | M29: 0.02 | N29: 0.02 | O29: 0.02 | P29: 0.02
D30: Worst Case | E30: % | L30: 0.04 | M30: 0.04 | N30: 0.04 | O30: 0.04 | P30: 0.04
B33: Sales Prices Scenarios
D35: Used in the Model | E35: $/unit | L35: {=INDEX(L36:L38,S_Scenarios)} -> 35000 | M35: {=INDEX(M36:M38,S_Scenarios)} -> 35500 | N35: {=INDEX(N36:N38,S_Scenarios)} -> 36000 | O35: {=INDEX(O36:O38,S_Scenarios)} -> 36500 | P35: {=INDEX(P36:P38,S_Scenarios)} -> 37000
D36: {=L_Scenarios} -> Base Case | E36: $/unit | L36: 35000 | M36: 35500 | N36: 36000 | O36: 36500 | P36: 37000
D37: Best Case | E37: $/unit | L37: 38500 | M37: 39050 | N37: 39600 | O37: 40150 | P37: 40700
D38: Worst Case | E38: $/unit | L38: 33250 | M38: 33725 | N38: 34200 | O38: 34675 | P38: 35150

Sheet Model
B2: Farley-Jamieson Inc. | I2: ="Financial Model: "&L5&" to "&P5 -> Financial Model: 2024 to 2028
B3: Model | I3: =IF(BS_Check=0,"BS Check: OK","BS Check: Error") -> BS Check: OK | K3: =Scenario_Used -> Scenario: Base Case
I4: Actual | J4: Actual | K4: Actual | L4: Forecast | M4: Forecast | N4: Forecast | O4: Forecast | P4: Forecast
E5: Unit | F5: Input | I5: 2021 | J5: =I5+1 -> 2022 | K5: =J5+1 -> 2023 | L5: =K5+1 -> 2024 | M5: =L5+1 -> 2025 | N5: =M5+1 -> 2026 | O5: =N5+1 -> 2027 | P5: =O5+1 -> 2028
B8: Farley-Jamieson Inc.
B9: Income Statement
B11: Millions for the Year Ended December 31
I13: 2021 | J13: =I13+1 -> 2022 | K13: =J13+1 -> 2023 | L13: =K13+1 -> 2024 | M13: =L13+1 -> 2025 | N13: =M13+1 -> 2026 | O13: =N13+1 -> 2027 | P13: =O13+1 -> 2028
B15: Revenue Growth | E15: % | J15: =J21/I21-1 -> 0.053532354 | K15: =K21/J21-1 -> -0.0213634 | L15: =L21/K21-1 -> 0.10653589 | M15: =M21/L21-1 -> 0.039642857 | N15: =N21/M21-1 -> 0.03943662 | O15: =O21/N21-1 -> 0.039236111 | P15: =P21/O21-1 -> 0.026851492
B16: COGS (% of revenue) | E16: % | I16: =I23/I$21 -> 0.63365505 | J16: =J23/J$21 -> 0.63120317 | K16: =K23/K$21 -> 0.62955734 | L16: =L23/L$21 -> 0.59480287 | M16: =M23/M$21 -> 0.59821235 | N16: =N23/N$21 -> 0.6018479 | O16: =O23/O$21 -> 0.60570957 | P16: =P23/P$21 -> 0.61248163
B17: SG&A (% of revenue) | E17: % | I17: =I24/I$21 -> 0.20545483 | J17: =J24/J$21 -> 0.20015207 | K17: =K24/K$21 -> 0.22276965 | L17: =L24/L$21 -> 0.20550017 | M17: =M24/M$21 -> 0.20359412 | N17: =N24/N$21 -> 0.20174578 | O17: =O24/O$21 -> 0.19995278 | P17: =P24/P$21 -> 0.20056587
D19: Gross Revenue | E19: =Currency -> $'m | I19: 5311.3 | J19: 5610 | K19: 5609.6 | L19: =L173 -> 6181.7832 | M19: =M173 -> 6423.5453 | N19: =N173 -> 6673.5404 | O19: =O173 -> 6932.0295 | P19: =P173 -> 7119.3427
D20: Freight & Warehousing | E20: =Currency -> $'m | I20: 192.9 | J20: 217.6 | K20: 332.4 | L20: =L174 -> 342.372 | M20: =M174 -> 352.64316 | N20: =N174 -> 363.22245 | O20: =O174 -> 374.11913 | P20: =P174 -> 385.3427
D21: Net Revenue | E21: =Currency -> $'m | I21: =I19-I20 -> 5118.4 | J21: =J19-J20 -> 5392.4 | K21: =K19-K20 -> 5277.2 | L21: =L19-L20 -> 5839.4112 | M21: =M19-M20 -> 6070.9021 | N21: =N19-N20 -> 6310.318 | O21: =O19-O20 -> 6557.9103 | P21: =P19-P20 -> 6734
D23: Cost of Sales | E23: =Currency -> $'m | I23: 3243.3 | J23: 3403.7 | K23: 3322.3 | L23: =L196 -> 3473.2985 | M23: =M196 -> 3631.6886 | N23: =N196 -> 3797.8516 | O23: =O196 -> 3972.1891 | P23: =P196 -> 4124.4513
D24: SG&A | E24: =Currency -> $'m | I24: 1051.6 | J24: 1079.3 | K24: 1175.6 | L24: =L198 -> 1200 | M24: =M198 -> 1236 | N24: =N198 -> 1273.08 | O24: =O198 -> 1311.2724 | P24: =P198 -> 1350.6106
D25: Total Costs | E25: =Currency -> $'m | I25: =SUM(I23:I24) -> 4294.9 | J25: =SUM(J23:J24) -> 4483 | K25: =SUM(K23:K24) -> 4497.9 | L25: =SUM(L23:L24) -> 4673.2985 | M25: =SUM(M23:M24) -> 4867.6886 | N25: =SUM(N23:N24) -> 5070.9316 | O25: =SUM(O23:O24) -> 5283.4615 | P25: =SUM(P23:P24) -> 5475.0619
D27: Cost Adjustments - Gain / (Loss) | E27: =Currency -> $'m | I27: -6.2 | J27: 0 | K27: 0 | L27: =Assumptions!L139 -> 0 | M27: =Assumptions!M139 -> 0 | N27: =Assumptions!N139 -> 0 | O27: =Assumptions!O139 -> 0 | P27: =Assumptions!P139 -> 0
D28: EBITDA | E28: =Currency -> $'m | I28: =I21-I25+I27 -> 817.3 | J28: =J21-J25+J27 -> 909.4 | K28: =K21-K25+K27 -> 779.3 | L28: =L21-L25+L27 -> 1166.1126 | M28: =M21-M25+M27 -> 1203.2135 | N28: =N21-N25+N27 -> 1239.3864 | O28: =O21-O25+O27 -> 1274.4489 | P28: =P21-P25+P27 -> 1258.9381
D30: Depreciation | E30: =Currency -> $'m | I30: 165.2 | J30: 151.9 | K30: 158.1 | L30: =L224 -> 18.25 | M30: =M224 -> 30.75 | N30: =N224 -> 43.25 | O30: =O224 -> 55.75 | P30: =P224 -> 68.25
D31: EBIT | E31: =Currency -> $'m | I31: =I28-I30 -> 652.1 | J31: =J28-J30 -> 757.5 | K31: =K28-K30 -> 621.2 | L31: =L28-L30 -> 1147.8626 | M31: =M28-M30 -> 1172.4635 | N31: =N28-N30 -> 1196.1364 | O31: =O28-O30 -> 1218.6989 | P31: =P28-P30 -> 1190.6881
D33: Cost Adjustments - Gain / (Loss) | E33: =Currency -> $'m | I33: 1.5 | J33: 0.6 | K33: 3.2 | L33: =Assumptions!L140 -> 0 | M33: =Assumptions!M140 -> 0 | N33: =Assumptions!N140 -> 0 | O33: =Assumptions!O140 -> 0 | P33: =Assumptions!P140 -> 0
D34: Net Interest Expense | E34: =Currency -> $'m | I34: 138.7 | J34: 216.6 | K34: 225.4 | L34: =L381 -> 218.30197 | M34: =M381 -> 205.26955 | N34: =N381 -> 189.45978 | O34: =O381 -> 172.74164 | P34: =P381 -> 154.97067
D35: EBT | E35: =Currency -> $'m | I35: =I31+I33-I34 -> 514.9 | J35: =J31+J33-J34 -> 541.5 | K35: =K31+K33-K34 -> 399 | L35: =L31+L33-L34 -> 929.56068 | M35: =M31+M33-M34 -> 967.19393 | N35: =N31+N33-N34 -> 1006.6766 | O35: =O31+O33-O34 -> 1045.9572 | P35: =P31+P33-P34 -> 1035.7174
D37: Current Taxes | E37: =Currency -> $'m | I37: 145.8 | J37: 159.4 | K37: 153.1 | L37: =L245 -> 290.34624 | M37: =M245 -> 303.51787 | N37: =N245 -> 317.3368 | O37: =O245 -> 331.08503 | P37: =P245 -> 327.5011
D38: Deferred Income Taxes | E38: =Currency -> $'m | I38: 23.4 | J38: 32.6 | K38: -21.3 | L38: =L246 -> 35 | M38: =M246 -> 35 | N38: =N246 -> 35 | O38: =O246 -> 35 | P38: =P246 -> 35
D39: Total Income Taxes | E39: =Currency -> $'m | I39: =SUM(I37:I38) -> 169.2 | J39: =SUM(J37:J38) -> 192 | K39: =SUM(K37:K38) -> 131.8 | L39: =SUM(L37:L38) -> 325.34624 | M39: =SUM(M37:M38) -> 338.51787 | N39: =SUM(N37:N38) -> 352.3368 | O39: =SUM(O37:O38) -> 366.08503 | P39: =SUM(P37:P38) -> 362.5011
D41: Net Income | E41: =Currency -> $'m | I41: =I35-I39 -> 345.7 | J41: =J35-J39 -> 349.5 | K41: =K35-K39 -> 267.2 | L41: =L35-L39 -> 604.21444 | M41: =M35-M39 -> 628.67605 | N41: =N35-N39 -> 654.33978 | O41: =O35-O39 -> 679.87219 | P41: =P35-P39 -> 673.21634
D43: Preferred Dividend | E43: =Currency -> $'m | I43: 0 | J43: 0 | K43: 0 | L43: =L294 -> 0 | M43: =M294 -> 2.3125 | N43: =N294 -> 4.625 | O43: =O294 -> 4.625 | P43: =P294 -> 4.625
D44: Net Income to Common | E44: =Currency -> $'m | I44: =I41-I43 -> 345.7 | J44: =J41-J43 -> 349.5 | K44: =K41-K43 -> 267.2 | L44: =L41-L43 -> 604.21444 | M44: =M41-M43 -> 626.36355 | N44: =N41-N43 -> 649.71478 | O44: =O41-O43 -> 675.24719 | P44: =P41-P43 -> 668.59134
D47: EBITDA Margin | E47: % | I47: =I28/I21 -> 0.15967881 | J47: =J28/J21 -> 0.16864476 | K47: =K28/K21 -> 0.14767301 | L47: =L28/L21 -> 0.19969696 | M47: =M28/M21 -> 0.19819352 | N47: =N28/N21 -> 0.19640633 | O47: =O28/O21 -> 0.19433765 | P47: =P28/P21 -> 0.1869525
C48: Dupont Analysis
D49: ROE | E49: % | I49: =I44/I135 -> 0.19213027 | J49: =J44/J135 -> 0.20526223 | K49: =K44/K135 -> 0.16599366 | L49: =L44/L135 -> 0.31759984 | M49: =M44/M135 -> 0.27720406 | N49: =N44/N135 -> 0.24226001 | O49: =O44/O135 -> 0.21636983 | P49: =P44/P135 -> 0.18805032
D50: Net Profit Margin | E50: % | I50: =I41/I21 -> 0.067540638 | J50: =J41/J21 -> 0.064813441 | K50: =K41/K21 -> 0.050632911 | L50: =L41/L21 -> 0.10347181 | M50: =M41/M21 -> 0.10355562 | N50: =N41/N21 -> 0.10369363 | O50: =O41/O21 -> 0.10367208 | P50: =P41/P21 -> 0.099972726
D51: Assets Turnover | E51: times | I51: =I21/I114 -> 0.92240043 | J51: =J21/J114 -> 0.94719831 | K51: =K21/K114 -> 0.9787092 | L51: =L21/L114 -> 1.0561663 | M51: =M21/M114 -> 1.0623035 | N51: =N21/N114 -> 1.057748 | O51: =O21/O114 -> 1.0519121 | P51: =P21/P114 -> 1.0368487
D52: Financial Leverage | E52: times | I52: =I114/I135 -> 3.0839771 | J52: =J114/J135 -> 3.3435132 | K52: =K114/K135 -> 3.3496925 | L52: =L114/L135 -> 2.9062029 | M52: =M114/M135 -> 2.5291682 | N52: =N114/N135 -> 2.2244776 | O52: =O114/O135 -> 1.9976526 | P52: =P114/P135 -> 1.8267161
B56: =$B$8 -> Farley-Jamieson Inc.
B57: Cash Flow Statement
B59: =$B$11 -> Millions for the Year Ended December 31
I61: =I$13 -> 2021 | J61: =J$13 -> 2022 | K61: =K$13 -> 2023 | L61: =L$13 -> 2024 | M61: =M$13 -> 2025 | N61: =N$13 -> 2026 | O61: =O$13 -> 2027 | P61: =P$13 -> 2028
B63: Operating Activities
D64: Net Income | E64: =Currency -> $'m | I64: 345.7 | J64: 349.5 | K64: 267.2 | L64: =L41 -> 604.21444 | M64: =M41 -> 628.67605 | N64: =N41 -> 654.33978 | O64: =O41 -> 679.87219 | P64: =P41 -> 673.21634
D65: Depreciation | E65: =Currency -> $'m | I65: 165.2 | J65: 151.9 | K65: 158.1 | L65: =L30 -> 18.25 | M65: =M30 -> 30.75 | N65: =N30 -> 43.25 | O65: =O30 -> 55.75 | P65: =P30 -> 68.25
D66: Deferred Income Taxes | E66: =Currency -> $'m | I66: 23.4 | J66: 32.6 | K66: -21.3 | L66: =L38 -> 35 | M66: =M38 -> 35 | N66: =N38 -> 35 | O66: =O38 -> 35 | P66: =P38 -> 35
D67: Changes in Working Capital | E67: =Currency -> $'m | I67: -37.6 | J67: -127.5 | K67: 5.7 | L67: =L281 -> -82.362707 | M67: =M281 -> -77.317317 | N67: =N281 -> -75.642706 | O67: =O281 -> -78.785097 | P67: =P281 -> -56.8781
D68: Other | E68: =Currency -> $'m | I68: -0.2 | J68: 1.1 | K68: -0.7 | L68: =Assumptions!L141 -> 0 | M68: =Assumptions!M141 -> 0 | N68: =Assumptions!N141 -> 0 | O68: =Assumptions!O141 -> 0 | P68: =Assumptions!P141 -> 0
D69: Operating Cash Flow | E69: =Currency -> $'m | I69: =SUM(I64:I68) -> 496.5 | J69: =SUM(J64:J68) -> 407.6 | K69: =SUM(K64:K68) -> 409 | L69: =SUM(L64:L68) -> 575.10174 | M69: =SUM(M64:M68) -> 617.10874 | N69: =SUM(N64:N68) -> 656.94707 | O69: =SUM(O64:O68) -> 691.83709 | P69: =SUM(P64:P68) -> 719.58824
B72: Investing Activities
D73: CAPEX | E73: =Currency -> $'m | I73: -220.2 | J73: -251.7 | K73: -207.4 | L73: =-L203 -> -225 | M73: =-M203 -> -225 | N73: =-N203 -> -225 | O73: =-O203 -> -225 | P73: =-P203 -> -225
D74: Asset Dispositions | E74: =Currency -> $'m | I74: 6.9 | J74: 8.9 | K74: 2.5 | L74: =Assumptions!L144 -> 0 | M74: =Assumptions!M144 -> 0 | N74: =Assumptions!N144 -> 0 | O74: =Assumptions!O144 -> 0 | P74: =Assumptions!P144 -> 0
D75: Other | E75: =Currency -> $'m | I75: 0 | J75: 0 | K75: 0 | L75: =Assumptions!L142 -> 0 | M75: =Assumptions!M142 -> 0 | N75: =Assumptions!N142 -> 0 | O75: =Assumptions!O142 -> 0 | P75: =Assumptions!P142 -> 0
D76: Investing Cash Flow | E76: =Currency -> $'m | I76: =SUM(I73:I75) -> -213.3 | J76: =SUM(J73:J75) -> -242.8 | K76: =SUM(K73:K75) -> -204.9 | L76: =SUM(L73:L75) -> -225 | M76: =SUM(M73:M75) -> -225 | N76: =SUM(N73:N75) -> -225 | O76: =SUM(O73:O75) -> -225 | P76: =SUM(P73:P75) -> -225
B79: Financing Activities
D80: =D359 -> Issue of Revolver / (Repayment) | I80: 0 | J80: 0 | K80: 0 | L80: =L359 -> 0 | M80: =M359 -> 0 | N80: =N359 -> 0 | O80: =O359 -> 0 | P80: =P359 -> 0
D81: Variable Rate Long Term Debt Issuance / (Repayment) | E81: =Currency -> $'m | I81: -25 | J81: 90.1 | K81: -29 | L81: =-L341 -> -75 | M81: =-M341 -> -75 | N81: =-N341 -> -75 | O81: =-O341 -> -75 | P81: =-P341 -> -75
D82: Fixed Rate Long Term Debt Issuance / (Repayment) | E82: =Currency -> $'m | I82: -235 | J82: 115 | K82: -130 | L82: =-L318 -> -150 | M82: =-M318 -> -150 | N82: =-N318 -> -150 | O82: =-O318 -> -150 | P82: =-P318 -> -150
D83: =D291 -> Issuance of Preferred Shares | I83: 0 | J83: 0 | K83: 0 | L83: =L291 -> 0 | M83: =M291 -> 50 | N83: =N291 -> 0 | O83: =O291 -> 0 | P83: =P291 -> 0
D84: Common Share Issuance / (Buy-Back) | E84: =Currency -> $'m | I84: -11.6 | J84: -338.6 | K84: -264 | L84: =L301 -> -100 | M84: =M301 -> -100 | N84: =N301 -> 0 | O84: =O301 -> 0 | P84: =P301 -> 0
D85: =D294 -> Preferred Shares Dividend | I85: 0 | J85: 0 | K85: 0 | L85: =-L294 -> 0 | M85: =-M294 -> -2.3125 | N85: =-N294 -> -4.625 | O85: =-O294 -> -4.625 | P85: =-P294 -> -4.625
D86: Common Share Dividends | E86: =Currency -> $'m | I86: -115.4 | J86: -108.2 | K86: -96.3 | L86: =-L307 -> -211.47506 | M86: =-M307 -> -219.22724 | N86: =-N307 -> -227.40017 | O86: =-O307 -> -236.33652 | P86: =-P307 -> -234.00697
D87: Other | E87: =Currency -> $'m | I87: 0.2 | J87: -0.7 | K87: 0.6 | L87: =Assumptions!L143 -> 0 | M87: =Assumptions!M143 -> 0 | N87: =Assumptions!N143 -> 0 | O87: =Assumptions!O143 -> 0 | P87: =Assumptions!P143 -> 0
D88: Financing Cash Flow | E88: =Currency -> $'m | I88: =SUM(I80:I87) -> -386.8 | J88: =SUM(J80:J87) -> -242.4 | K88: =SUM(K80:K87) -> -518.7 | L88: =SUM(L80:L87) -> -536.47506 | M88: =SUM(M80:M87) -> -496.53974 | N88: =SUM(N80:N87) -> -457.02517 | O88: =SUM(O80:O87) -> -465.96152 | P88: =SUM(P80:P87) -> -463.63197
D90: Change in Cash Position | E90: =Currency -> $'m | I90: =I88+I76+I69 -> -103.6 | J90: =J88+J76+J69 -> -77.6 | K90: =K88+K76+K69 -> -314.6 | L90: =L88+L76+L69 -> -186.37332 | M90: =M88+M76+M69 -> -104.43101 | N90: =N88+N76+N69 -> -25.078101 | O90: =O88+O76+O69 -> 0.87557669 | P90: =P88+P76+P69 -> 30.956268
D91: Beginning Cash | E91: =Currency -> $'m | I91: 905.4 | J91: =I92 -> 801.8 | K91: =J92 -> 724.2 | L91: =K92 -> 409.6 | M91: =L92 -> 223.22668 | N91: =M92 -> 118.79567 | O91: =N92 -> 93.717574 | P91: =O92 -> 94.59315
D92: Ending Cash | E92: =Currency -> $'m | I92: =I91+I90 -> 801.8 | J92: =J91+J90 -> 724.2 | K92: =K91+K90 -> 409.6 | L92: =L91+L90 -> 223.22668 | M92: =M91+M90 -> 118.79567 | N92: =N91+N90 -> 93.717574 | O92: =O91+O90 -> 94.59315 | P92: =P91+P90 -> 125.54942
B96: =$B$8 -> Farley-Jamieson Inc.
B97: Balance Sheet
B99: =$B$11 -> Millions for the Year Ended December 31
I100: =I$13 -> 2021 | J100: =J$13 -> 2022 | K100: =K$13 -> 2023
B101: ASSETS
D102: Cash and Equivalents | E102: =Currency -> $'m | I102: 801.8 | J102: 724.2 | K102: 409.6 | L102: =L92 -> 223.22668 | M102: =M92 -> 118.79567 | N102: =N92 -> 93.717574 | O102: =O92 -> 94.59315 | P102: =P92 -> 125.54942
D103: Accounts Receivable | E103: =Currency -> $'m | I103: 787.2 | J103: 882.6 | K103: 869.2 | L103: =L261 -> 935.98751 | M103: =M261 -> 975.75874 | N103: =N261 -> 1014.2394 | O103: =O261 -> 1054.0342 | P103: =P261 -> 1079.3794
D104: Inventory | E104: =Currency -> $'m | I104: 915.9 | J104: 951 | K104: 929.9 | L104: =L262 -> 971.82445 | M104: =M262 -> 1018.9257 | N104: =N262 -> 1065.5453 | O104: =O262 -> 1114.4583 | P104: =P262 -> 1154.0162
D105: Other | E105: =Currency -> $'m | I105: 185.8 | J105: 181.3 | K105: 183.7 | L105: =L263 -> 191.48617 | M105: =M263 -> 200.76691 | N105: =N263 -> 209.95273 | O105: =O263 -> 219.59044 | P105: =P263 -> 227.38483
D106: Total Current Assets | E106: =Currency -> $'m | I106: =SUM(I102:I105) -> 2690.7 | J106: =SUM(J102:J105) -> 2739.1 | K106: =SUM(K102:K105) -> 2392.4 | L106: =SUM(L102:L105) -> 2322.5248 | M106: =SUM(M102:M105) -> 2314.2471 | N106: =SUM(N102:N105) -> 2383.455 | O106: =SUM(O102:O105) -> 2482.6761 | P106: =SUM(P102:P105) -> 2586.3298
D108: Net PP&E | E108: =Currency -> $'m | I108: 1885.5 | J108: 1985.3 | K108: 2034.6 | L108: =L230 -> 2241.35 | M108: =M230 -> 2435.6 | N108: =N230 -> 2617.35 | O108: =O230 -> 2786.6 | P108: =P230 -> 2943.35
D109: Goodwill | E109: =Currency -> $'m | I109: 465.7 | J109: 463 | K109: 460.6 | L109: =K109+Assumptions!L149 -> 460.6 | M109: =L109+Assumptions!M149 -> 460.6 | N109: =M109+Assumptions!N149 -> 460.6 | O109: =N109+Assumptions!O149 -> 460.6 | P109: =O109+Assumptions!P149 -> 460.6
D110: Intangibles | E110: =Currency -> $'m | I110: 330.7 | J110: 335.4 | K110: 333.5 | L110: =K110+Assumptions!L145 -> 333.5 | M110: =L110+Assumptions!M145 -> 333.5 | N110: =M110+Assumptions!N145 -> 333.5 | O110: =N110+Assumptions!O145 -> 333.5 | P110: =O110+Assumptions!P145 -> 333.5
D111: Other | E111: =Currency -> $'m | I111: 176.4 | J111: 170.2 | K111: 170.9 | L111: =K111+Assumptions!L146 -> 170.9 | M111: =L111+Assumptions!M146 -> 170.9 | N111: =M111+Assumptions!N146 -> 170.9 | O111: =N111+Assumptions!O146 -> 170.9 | P111: =O111+Assumptions!P146 -> 170.9
D112: Total Long Term Assets | E112: =Currency -> $'m | I112: =SUM(I108:I111) -> 2858.3 | J112: =SUM(J108:J111) -> 2953.9 | K112: =SUM(K108:K111) -> 2999.6 | L112: =SUM(L108:L111) -> 3206.35 | M112: =SUM(M108:M111) -> 3400.6 | N112: =SUM(N108:N111) -> 3582.35 | O112: =SUM(O108:O111) -> 3751.6 | P112: =SUM(P108:P111) -> 3908.35
D114: Total Assets | E114: =Currency -> $'m | I114: =I106+I112 -> 5549 | J114: =J106+J112 -> 5693 | K114: =K106+K112 -> 5392 | L114: =L106+L112 -> 5528.8748 | M114: =M106+M112 -> 5714.8471 | N114: =N106+N112 -> 5965.805 | O114: =O106+O112 -> 6234.2761 | P114: =P106+P112 -> 6494.6798
B117: LIABILITIES AND EQUITY
D118: Revolver | E118: =Currency -> $'m | I118: 0 | J118: 0 | K118: 0 | L118: =L360 -> 0 | M118: =M360 -> 0 | N118: =N360 -> 0 | O118: =O360 -> 0 | P118: =P360 -> 0
D119: Accounts Payable | E119: =Currency -> $'m | I119: 375 | J119: 378 | K119: 349.2 | L119: =L266 -> 383.08165 | M119: =M266 -> 401.64842 | N119: =N266 -> 420.0253 | O119: =O266 -> 439.30624 | P119: =P266 -> 454.89946
D120: Other | E120: =Currency -> $'m | I120: 4.9 | J120: 5.8 | K120: 5.3 | L120: =L267 -> 5.5537729 | M120: =M267 -> 5.822947 | N120: =N267 -> 6.089368 | O120: =O267 -> 6.3688957 | P120: =P267 -> 6.5949603
D121: Total Current Liabilities | E121: =Currency -> $'m | I121: =SUM(I118:I120) -> 379.9 | J121: =SUM(J118:J120) -> 383.8 | K121: =SUM(K118:K120) -> 354.5 | L121: =SUM(L118:L120) -> 388.63542 | M121: =SUM(M118:M120) -> 407.47137 | N121: =SUM(N118:N120) -> 426.11467 | O121: =SUM(O118:O120) -> 445.67513 | P121: =SUM(P118:P120) -> 461.49442
D123: Variable Rate Long Term Debt | E123: =Currency -> $'m | I123: 802.5 | J123: 892.6 | K123: 863.6 | L123: =L342 -> 788.6 | M123: =M342 -> 713.6 | N123: =N342 -> 638.6 | O123: =O342 -> 563.6 | P123: =P342 -> 488.6
D124: Fixed Rate Long Term Debt | E124: =Currency -> $'m | I124: 2455.6 | J124: 2570.6 | K124: 2440.6 | L124: =L319 -> 2290.6 | M124: =M319 -> 2140.6 | N124: =N319 -> 1990.6 | O124: =O319 -> 1840.6 | P124: =P319 -> 1690.6
D125: Deferred Income Taxes | E125: =Currency -> $'m | I125: 99.3 | J125: 131.9 | K125: 110.6 | L125: =K125+L66 -> 145.6 | M125: =L125+M66 -> 180.6 | N125: =M125+N66 -> 215.6 | O125: =N125+O66 -> 250.6 | P125: =O125+P66 -> 285.6
D126: Other | E126: =Currency -> $'m | I126: 12.4 | J126: 11.4 | K126: 13 | L126: =K126+Assumptions!L147 -> 13 | M126: =L126+Assumptions!M147 -> 13 | N126: =M126+Assumptions!N147 -> 13 | O126: =N126+Assumptions!O147 -> 13 | P126: =O126+Assumptions!P147 -> 13
D127: Total Long Term Liabilities | E127: =Currency -> $'m | I127: =SUM(I123:I126) -> 3369.8 | J127: =SUM(J123:J126) -> 3606.5 | K127: =SUM(K123:K126) -> 3427.8 | L127: =SUM(L123:L126) -> 3237.8 | M127: =SUM(M123:M126) -> 3047.8 | N127: =SUM(N123:N126) -> 2857.8 | O127: =SUM(O123:O126) -> 2667.8 | P127: =SUM(P123:P126) -> 2477.8
D129: Total Liabilities | E129: =Currency -> $'m | I129: =I121+I127 -> 3749.7 | J129: =J121+J127 -> 3990.3 | K129: =K121+K127 -> 3782.3 | L129: =L121+L127 -> 3626.4354 | M129: =M121+M127 -> 3455.2714 | N129: =N121+N127 -> 3283.9147 | O129: =O121+O127 -> 3113.4751 | P129: =P121+P127 -> 2939.2944
D131: Preferred Shares | E131: =Currency -> $'m | I131: 0 | J131: 0 | K131: 0 | L131: =L292 -> 0 | M131: =M292 -> 50 | N131: =N292 -> 50 | O131: =O292 -> 50 | P131: =P292 -> 50
D132: Common Shares | E132: =Currency -> $'m | I132: 951.7 | J132: 613.1 | K132: 349.1 | L132: =L302 -> 249.1 | M132: =M302 -> 149.1 | N132: =N302 -> 149.1 | O132: =O302 -> 149.1 | P132: =P302 -> 149.1
D133: Retained Earnings | E133: =Currency -> $'m | I133: 842.4 | J133: 1083.7 | K133: 1254.6 | L133: =L308 -> 1647.3394 | M133: =M308 -> 2054.4757 | N133: =N308 -> 2476.7903 | O133: =O308 -> 2915.701 | P133: =P308 -> 3350.2853
D134: Other | E134: =Currency -> $'m | I134: 5.2 | J134: 5.9 | K134: 6 | L134: =K134+Assumptions!L148 -> 6 | M134: =L134+Assumptions!M148 -> 6 | N134: =M134+Assumptions!N148 -> 6 | O134: =N134+Assumptions!O148 -> 6 | P134: =O134+Assumptions!P148 -> 6
D135: Shareholder's Equity | E135: =Currency -> $'m | I135: =SUM(I131:I134) -> 1799.3 | J135: =SUM(J131:J134) -> 1702.7 | K135: =SUM(K131:K134) -> 1609.7 | L135: =SUM(L131:L134) -> 1902.4394 | M135: =SUM(M131:M134) -> 2259.5757 | N135: =SUM(N131:N134) -> 2681.8903 | O135: =SUM(O131:O134) -> 3120.801 | P135: =SUM(P131:P134) -> 3555.3853
B137: Total Liabilities and Equity | E137: =Currency -> $'m | I137: =I135+I129 -> 5549 | J137: =J135+J129 -> 5693 | K137: =K135+K129 -> 5392 | L137: =L135+L129 -> 5528.8748 | M137: =M135+M129 -> 5714.8471 | N137: =N135+N129 -> 5965.805 | O137: =O135+O129 -> 6234.2761 | P137: =P135+P129 -> 6494.6798
D141: Check | E141: =SUM(I141:P141) -> 0 | I141: =I137-I114 -> 0 | J141: =J137-J114 -> 0 | K141: =K137-K114 -> 0 | L141: =L137-L114 -> 0 | M141: =M137-M114 -> 0 | N141: =N137-N114 -> 0 | O141: =O137-O114 -> 0 | P141: =P137-P114 -> 0
A145: SCHEDULES & CALCULATIONS
...
